setup.cfg
setup.py
pyhangouts/__init__.py
pyhangouts/client.py
pyhangouts.egg-info/PKG-INFO
pyhangouts.egg-info/SOURCES.txt
pyhangouts.egg-info/dependency_links.txt
pyhangouts.egg-info/requires.txt
pyhangouts.egg-info/top_level.txt