Metadata-Version: 1.1
Name: pyhangouts
Version: 0.0.1
Summary: A selenium-based client for Google Hangouts
Home-page: https://github.com/amigcamel/pyhangouts.git
Author: Aji Liu
Author-email: amigcamel@gmail.com
License: UNKNOWN
Download-URL: https://github.com/amigcamel/pyhangouts/tarball/0.0.1
Platform: UNKNOWN
